interface_tester/__init__.py
interface_tester/collector.py
interface_tester/errors.py
interface_tester/interface_test.py
interface_tester/plugin.py
interface_tester/py.typed
interface_tester/schema_base.py
interface_tester/cli/__init__.py
interface_tester/cli/discover.py
interface_tester/cli/main.py
pytest_interface_tester-3.4.0.dist-info/METADATA
pytest_interface_tester-3.4.0.dist-info/WHEEL
pytest_interface_tester-3.4.0.dist-info/entry_points.txt
pytest_interface_tester-3.4.0.dist-info/top_level.txt
pytest_interface_tester-3.4.0.dist-info/RECORD
