Metadata-Version: 2.4
Name: pytest-interface-tester
Version: 3.4.0
Summary: Pytest plugin for checking charm relation interface protocol compliance.
Author-email: Pietro Pasotti <pietro.pasotti@canonical.com>
License: Apache-2.0
Project-URL: Homepage, https://github.com/canonical/pytest-interface-tester
Keywords: juju,relation interfaces
Classifier: Development Status :: 4 - Beta
Classifier: Framework :: Pytest
Classifier: Intended Audience :: Developers
Classifier: Topic :: Software Development :: Testing
Classifier: Programming Language :: Python
Classifier: Programming Language :: Python :: 3
Classifier: Programming Language :: Python :: 3.5
Classifier: Programming Language :: Python :: 3.6
Classifier: Programming Language :: Python :: 3.7
Classifier: Programming Language :: Python :: 3.8
Classifier: Programming Language :: Python :: 3 :: Only
Classifier: Programming Language :: Python :: Implementation :: CPython
Classifier: Programming Language :: Python :: Implementation :: PyPy
Classifier: Operating System :: OS Independent
Requires-Python: >=3.8
Requires-Dist: pydantic>=1.10.7
Requires-Dist: typer==0.7.0
Requires-Dist: ops-scenario>=7.0.1
Requires-Dist: pytest
